pyohhell/__init__.py
pyohhell/game_engine.py
pyohhell/game_state.py
pyohhell/player.py
pyohhell-0.1.0.dist-info/LICENSE
pyohhell-0.1.0.dist-info/METADATA
pyohhell-0.1.0.dist-info/WHEEL
pyohhell-0.1.0.dist-info/RECORD
