Metadata-Version: 2.1
Name: pyohhell
Version: 0.1.0
Summary: A Oh Hell card game engine
License: MIT
Author: amaurylekens
Requires-Python: >=3.9,<4.0
Classifier: License :: OSI Approved :: MIT License
Classifier: Programming Language :: Python :: 3
Classifier: Programming Language :: Python :: 3.9
Classifier: Programming Language :: Python :: 3.10
Classifier: Programming Language :: Python :: 3.11
Classifier: Programming Language :: Python :: 3.12
Requires-Dist: pydecklib (>=0.1.1,<0.2.0)
